bleak_fsm/__init__.py
bleak_fsm/bleak_model.py
bleak_fsm-0.2.1.dist-info/LICENSE
bleak_fsm-0.2.1.dist-info/METADATA
bleak_fsm-0.2.1.dist-info/WHEEL
bleak_fsm-0.2.1.dist-info/RECORD
