Metadata-Version: 2.1
Name: bleak-fsm
Version: 0.2.1
Summary: A Finite State Machine abstraction over the Bleak Bluetooth library for simplified state management in production Python applications.
License: MIT
Author: tensorturtle
Author-email: tensorturtle@gmail.com
Requires-Python: >=3.8,<3.13
Classifier: License :: OSI Approved :: MIT License
Classifier: Programming Language :: Python :: 3
Classifier: Programming Language :: Python :: 3.8
Classifier: Programming Language :: Python :: 3.9
Classifier: Programming Language :: Python :: 3.10
Classifier: Programming Language :: Python :: 3.11
Classifier: Programming Language :: Python :: 3.12
Requires-Dist: bleak (>=0.21.1,<0.22.0)
Requires-Dist: transitions (>=0.9.0,<0.10.0)
